jacobi_realsense_camera_driver-0.4.4.dist-info/licenses/LICENSE
jacobi_realsense_driver/__init__.py
jacobi_realsense_driver/realsense_camera_driver.py
jacobi_realsense_camera_driver-0.4.4.dist-info/METADATA
jacobi_realsense_camera_driver-0.4.4.dist-info/WHEEL
jacobi_realsense_camera_driver-0.4.4.dist-info/top_level.txt
jacobi_realsense_camera_driver-0.4.4.dist-info/RECORD
