Metadata-Version: 2.4
Name: jacobi-realsense-camera-driver
Version: 0.4.4
Summary: Driver for Intel Realsense cameras.
Author-email: Lars Berscheid <lars.berscheid@jacobirobotics.com>, Andreas ten Pas <andreas.tenpas@jacobirobotics.com>
License: Copyright (c) 2024 Jacobi Robotics Inc.
Project-URL: homepage, https://www.jacobirobotics.com
Project-URL: documentation, https://docs.jacobirobotics.com
Keywords: robotics,computer-vision
Classifier: Development Status :: 4 - Beta
Classifier: Intended Audience :: Science/Research
Classifier: Topic :: Scientific/Engineering
Classifier: License :: Other/Proprietary License
Classifier: Programming Language :: Python
Requires-Python: >=3.10
License-File: LICENSE
Requires-Dist: jacobi-vision
Requires-Dist: pyrealsense2~=2.55
Dynamic: license-file
